{
  "output_dir": "experiments/eg_rsa_landing_v2_1_source_aware_bootstrap_check",
  "num_iterations": 1,
  "iterations": [
    {
      "iteration": 0,
      "task_score": 0.7217248883088337,
      "semantic_score": 0.7217248883088337,
      "selection_score": 1.2434497766176675,
      "hack_score": 0.2,
      "failure_modes": "shaping_goal_mismatch",
      "dominant_component": "horizontal_approach",
      "dominant_component_ratio": 0.49015827678432544,
      "benign_terminal_dominance": false,
      "terminal_goal_evidence": false,
      "reward_repetition_risk": false,
      "success_episode_rate": 0.0,
      "terminal_reward_paid_episode_rate": 0.0,
      "stable_landing_episode_rate": 0.0,
      "safe_contact_episode_rate": 0.0,
      "contact_toggle_mean": 68.0,
      "contact_toggle_max": 68.0,
      "posthoc_return_mean": -839.6222159907935,
      "posthoc_return_std": 0.0,
      "posthoc_episode_length_mean": 165.0,
      "edit_generated": false,
      "edit_decision": "edit",
      "edit_status": "skipped",
      "edit_valid": "skipped",
      "edit_errors": "",
      "edit_count": 0,
      "edit_diagnosis": "Final iteration; edit generation skipped.",
      "memory_failure_modes": "shaping_goal_mismatch",
      "memory_outcome_status": "not_applicable",
      "outcome_task_delta": null,
      "outcome_semantic_delta": null,
      "outcome_selection_delta": null,
      "outcome_hack_delta": null,
      "component_ratio__horizontal_approach": 0.49015827678432544,
      "component_trigger__horizontal_approach": 0.9958333333333333,
      "component_ratio__vertical_approach": 0.0,
      "component_trigger__vertical_approach": 0.0,
      "component_ratio__descent_rate": 6.952305530837949e-09,
      "component_trigger__descent_rate": 0.0375,
      "component_ratio__attitude_stability": 0.4581407364090744,
      "component_trigger__attitude_stability": 1.0,
      "component_ratio__control_cost": 0.05170097985428347,
      "component_trigger__control_cost": 0.8541666666666666,
      "component_ratio__landing_bonus": 0.0,
      "component_trigger__landing_bonus": 0.0
    }
  ],
  "best_by_task_score": {
    "iteration": 0,
    "task_score": 0.7217248883088337,
    "semantic_score": 0.7217248883088337,
    "selection_score": 1.2434497766176675,
    "hack_score": 0.2,
    "failure_modes": "shaping_goal_mismatch",
    "dominant_component": "horizontal_approach",
    "dominant_component_ratio": 0.49015827678432544,
    "benign_terminal_dominance": false,
    "terminal_goal_evidence": false,
    "reward_repetition_risk": false,
    "success_episode_rate": 0.0,
    "terminal_reward_paid_episode_rate": 0.0,
    "stable_landing_episode_rate": 0.0,
    "safe_contact_episode_rate": 0.0,
    "contact_toggle_mean": 68.0,
    "contact_toggle_max": 68.0,
    "posthoc_return_mean": -839.6222159907935,
    "posthoc_return_std": 0.0,
    "posthoc_episode_length_mean": 165.0,
    "edit_generated": false,
    "edit_decision": "edit",
    "edit_status": "skipped",
    "edit_valid": "skipped",
    "edit_errors": "",
    "edit_count": 0,
    "edit_diagnosis": "Final iteration; edit generation skipped.",
    "memory_failure_modes": "shaping_goal_mismatch",
    "memory_outcome_status": "not_applicable",
    "outcome_task_delta": null,
    "outcome_semantic_delta": null,
    "outcome_selection_delta": null,
    "outcome_hack_delta": null,
    "component_ratio__horizontal_approach": 0.49015827678432544,
    "component_trigger__horizontal_approach": 0.9958333333333333,
    "component_ratio__vertical_approach": 0.0,
    "component_trigger__vertical_approach": 0.0,
    "component_ratio__descent_rate": 6.952305530837949e-09,
    "component_trigger__descent_rate": 0.0375,
    "component_ratio__attitude_stability": 0.4581407364090744,
    "component_trigger__attitude_stability": 1.0,
    "component_ratio__control_cost": 0.05170097985428347,
    "component_trigger__control_cost": 0.8541666666666666,
    "component_ratio__landing_bonus": 0.0,
    "component_trigger__landing_bonus": 0.0
  },
  "best_by_selection_score": {
    "iteration": 0,
    "task_score": 0.7217248883088337,
    "semantic_score": 0.7217248883088337,
    "selection_score": 1.2434497766176675,
    "hack_score": 0.2,
    "failure_modes": "shaping_goal_mismatch",
    "dominant_component": "horizontal_approach",
    "dominant_component_ratio": 0.49015827678432544,
    "benign_terminal_dominance": false,
    "terminal_goal_evidence": false,
    "reward_repetition_risk": false,
    "success_episode_rate": 0.0,
    "terminal_reward_paid_episode_rate": 0.0,
    "stable_landing_episode_rate": 0.0,
    "safe_contact_episode_rate": 0.0,
    "contact_toggle_mean": 68.0,
    "contact_toggle_max": 68.0,
    "posthoc_return_mean": -839.6222159907935,
    "posthoc_return_std": 0.0,
    "posthoc_episode_length_mean": 165.0,
    "edit_generated": false,
    "edit_decision": "edit",
    "edit_status": "skipped",
    "edit_valid": "skipped",
    "edit_errors": "",
    "edit_count": 0,
    "edit_diagnosis": "Final iteration; edit generation skipped.",
    "memory_failure_modes": "shaping_goal_mismatch",
    "memory_outcome_status": "not_applicable",
    "outcome_task_delta": null,
    "outcome_semantic_delta": null,
    "outcome_selection_delta": null,
    "outcome_hack_delta": null,
    "component_ratio__horizontal_approach": 0.49015827678432544,
    "component_trigger__horizontal_approach": 0.9958333333333333,
    "component_ratio__vertical_approach": 0.0,
    "component_trigger__vertical_approach": 0.0,
    "component_ratio__descent_rate": 6.952305530837949e-09,
    "component_trigger__descent_rate": 0.0375,
    "component_ratio__attitude_stability": 0.4581407364090744,
    "component_trigger__attitude_stability": 1.0,
    "component_ratio__control_cost": 0.05170097985428347,
    "component_trigger__control_cost": 0.8541666666666666,
    "component_ratio__landing_bonus": 0.0,
    "component_trigger__landing_bonus": 0.0
  },
  "best_by_semantic_score": {
    "iteration": 0,
    "task_score": 0.7217248883088337,
    "semantic_score": 0.7217248883088337,
    "selection_score": 1.2434497766176675,
    "hack_score": 0.2,
    "failure_modes": "shaping_goal_mismatch",
    "dominant_component": "horizontal_approach",
    "dominant_component_ratio": 0.49015827678432544,
    "benign_terminal_dominance": false,
    "terminal_goal_evidence": false,
    "reward_repetition_risk": false,
    "success_episode_rate": 0.0,
    "terminal_reward_paid_episode_rate": 0.0,
    "stable_landing_episode_rate": 0.0,
    "safe_contact_episode_rate": 0.0,
    "contact_toggle_mean": 68.0,
    "contact_toggle_max": 68.0,
    "posthoc_return_mean": -839.6222159907935,
    "posthoc_return_std": 0.0,
    "posthoc_episode_length_mean": 165.0,
    "edit_generated": false,
    "edit_decision": "edit",
    "edit_status": "skipped",
    "edit_valid": "skipped",
    "edit_errors": "",
    "edit_count": 0,
    "edit_diagnosis": "Final iteration; edit generation skipped.",
    "memory_failure_modes": "shaping_goal_mismatch",
    "memory_outcome_status": "not_applicable",
    "outcome_task_delta": null,
    "outcome_semantic_delta": null,
    "outcome_selection_delta": null,
    "outcome_hack_delta": null,
    "component_ratio__horizontal_approach": 0.49015827678432544,
    "component_trigger__horizontal_approach": 0.9958333333333333,
    "component_ratio__vertical_approach": 0.0,
    "component_trigger__vertical_approach": 0.0,
    "component_ratio__descent_rate": 6.952305530837949e-09,
    "component_trigger__descent_rate": 0.0375,
    "component_ratio__attitude_stability": 0.4581407364090744,
    "component_trigger__attitude_stability": 1.0,
    "component_ratio__control_cost": 0.05170097985428347,
    "component_trigger__control_cost": 0.8541666666666666,
    "component_ratio__landing_bonus": 0.0,
    "component_trigger__landing_bonus": 0.0
  },
  "best_by_posthoc_return": {
    "iteration": 0,
    "task_score": 0.7217248883088337,
    "semantic_score": 0.7217248883088337,
    "selection_score": 1.2434497766176675,
    "hack_score": 0.2,
    "failure_modes": "shaping_goal_mismatch",
    "dominant_component": "horizontal_approach",
    "dominant_component_ratio": 0.49015827678432544,
    "benign_terminal_dominance": false,
    "terminal_goal_evidence": false,
    "reward_repetition_risk": false,
    "success_episode_rate": 0.0,
    "terminal_reward_paid_episode_rate": 0.0,
    "stable_landing_episode_rate": 0.0,
    "safe_contact_episode_rate": 0.0,
    "contact_toggle_mean": 68.0,
    "contact_toggle_max": 68.0,
    "posthoc_return_mean": -839.6222159907935,
    "posthoc_return_std": 0.0,
    "posthoc_episode_length_mean": 165.0,
    "edit_generated": false,
    "edit_decision": "edit",
    "edit_status": "skipped",
    "edit_valid": "skipped",
    "edit_errors": "",
    "edit_count": 0,
    "edit_diagnosis": "Final iteration; edit generation skipped.",
    "memory_failure_modes": "shaping_goal_mismatch",
    "memory_outcome_status": "not_applicable",
    "outcome_task_delta": null,
    "outcome_semantic_delta": null,
    "outcome_selection_delta": null,
    "outcome_hack_delta": null,
    "component_ratio__horizontal_approach": 0.49015827678432544,
    "component_trigger__horizontal_approach": 0.9958333333333333,
    "component_ratio__vertical_approach": 0.0,
    "component_trigger__vertical_approach": 0.0,
    "component_ratio__descent_rate": 6.952305530837949e-09,
    "component_trigger__descent_rate": 0.0375,
    "component_ratio__attitude_stability": 0.4581407364090744,
    "component_trigger__attitude_stability": 1.0,
    "component_ratio__control_cost": 0.05170097985428347,
    "component_trigger__control_cost": 0.8541666666666666,
    "component_ratio__landing_bonus": 0.0,
    "component_trigger__landing_bonus": 0.0
  }
}